{
	"pages": [
		//pages数组中第一项表示应用启动页，参考：https://uniapp.dcloud.io/collocation/pages

		{
			"path": "pages/task/task",
			"style": {
				"enablePullDownRefresh": true,
				"backgroundColor": "#022456",
				"backgroundTextStyle": "light"
			}
		},
		{
			"path": "pages/task_details/task_details",
			"style": {
				"navigationBarTitleText": "设施点详情"
			}
		}

	],
	"globalStyle": {
		"navigationBarTextStyle": "white",
		"navigationBarTitleText": "上海市社区体育设施",
		"navigationBarBackgroundColor": "#022456",
		"backgroundColor": "#1E90FF"
	}
}
